periodic_table_cli/__init__.py
periodic_table_cli/app.py
periodic_table_cli/chart_processor.py
periodic_table_cli/cli.py
periodic_table_cli/colors.py
periodic_table_cli/dashboard.py
periodic_table_cli/data.json
periodic_table_cli/data_processor.py
periodic_table_cli/renderer.py
periodic_table_cli/search_processor.py
periodic_table_cli/state_controller.py
periodic_table_cli/tables.py
periodic_table_cli/utils.py
periodic_table_cli-2.1.3.dist-info/LICENSE
periodic_table_cli-2.1.3.dist-info/METADATA
periodic_table_cli-2.1.3.dist-info/WHEEL
periodic_table_cli-2.1.3.dist-info/entry_points.txt
periodic_table_cli-2.1.3.dist-info/top_level.txt
periodic_table_cli-2.1.3.dist-info/RECORD
