Metadata-Version: 2.1
Name: periodic-table-cli
Version: 2.1.3
Summary: An interactive Periodic Table of Elements app for the console!
Author-email: Spiro Metaxas <spirometaxas@outlook.com>
Maintainer-email: Spiro Metaxas <spirometaxas@outlook.com>
License: MIT License
Project-URL: Homepage, https://spirometaxas.com/projects/periodic-table-cli/
Project-URL: Repository, https://github.com/spirometaxas/periodic-table-cli-py
Keywords: Periodic Table,Periodic Table of Elements,periodic,periodic-table-cli,Chemistry,elements,atoms,atomic,cli,console,terminal,shell,unicode
Classifier: Development Status :: 5 - Production/Stable
Classifier: Environment :: Console
Classifier: Environment :: Console :: Curses
Classifier: Intended Audience :: Education
Classifier: Intended Audience :: Science/Research
Classifier: Topic :: Education
Classifier: Topic :: Scientific/Engineering :: Bio-Informatics
Classifier: Topic :: Scientific/Engineering :: Chemistry
Classifier: Topic :: Scientific/Engineering :: Medical Science Apps.
Classifier: Topic :: Terminals
Classifier: License :: OSI Approved :: MIT License
Classifier: Programming Language :: Python
Classifier: Programming Language :: Python :: 3.13
Classifier: Programming Language :: Python :: 3.12
Classifier: Programming Language :: Python :: 3.11
Classifier: Programming Language :: Python :: 3.10
Classifier: Programming Language :: Python :: 3.9
Classifier: Programming Language :: Python :: 3.8
Classifier: Programming Language :: Python :: 3
Classifier: Operating System :: OS Independent
Requires-Python: >=3.8
License-File: LICENSE
Requires-Dist: windows-curses ; platform_system == "Windows"
